{
  "entities": [
    {"id": "C201", "title": "Значение", "category": "concepts", "layer": "Знаковый", "status": "stub",
     "definition": "Объективное содержание знака в знаковой структуре X/λ; промежуточное звено между знаком и смыслом (Кн.3).",
     "relates": [{"to": "C069", "name": "Знак", "type": "содержательная"}, {"to": "C010", "name": "Смысл", "type": "содержательная"}]},
    {"id": "C202", "title": "Замещение", "category": "concepts", "layer": "Знаковый", "status": "stub",
     "definition": "Исходная операция знаковой ситуации: знак замещает объект; основание моделирования (Кн.3).",
     "relates": [{"to": "C069", "name": "Знак", "type": "содержательная"}, {"to": "C203", "name": "Моделирование", "type": "генетическая"}]},
    {"id": "C203", "title": "Моделирование", "category": "concepts", "layer": "Знаковый", "status": "stub",
     "definition": "Развитие замещения в построение модели; ступень к теоретическому знанию (Кн.3).",
     "relates": [{"to": "C202", "name": "Замещение", "type": "генетическая"}]},
    {"id": "C204", "title": "Диалектическая логика", "category": "concepts", "layer": "Логический", "status": "stub",
     "definition": "Промежуточная ступень между формальной и содержательно-генетической логикой (Кн.2).",
     "relates": [{"to": "C123", "name": "Формальная логика", "type": "генетическая"}, {"to": "C101", "name": "Содержательно-генетическая логика", "type": "генетическая"}]},
    {"id": "C205", "title": "Педагогика", "category": "concepts", "layer": "Подход", "status": "stub",
     "definition": "Прикладной выход линии подхода: верстак+кладовая → культуротехника → педагогика (Кн.1).",
     "relates": [{"to": "C087", "name": "Подход", "type": "содержательная"}]},
    {"id": "C206", "title": "Коммуникативная ситуация", "category": "concepts", "layer": "Знаковый", "status": "stub",
     "definition": "Расширение знаковой ситуации до взаимодействия деятелей; завершает знаковый слой (Кн.3).",
     "relates": [{"to": "C008", "name": "Коммуникация", "type": "содержательная"}, {"to": "C201", "name": "Значение", "type": "содержательная"}]}
  ]
}
